logging_color_formatter/__init__.py
logging_color_formatter-1.1.0.dist-info/LICENSE
logging_color_formatter-1.1.0.dist-info/METADATA
logging_color_formatter-1.1.0.dist-info/WHEEL
logging_color_formatter-1.1.0.dist-info/top_level.txt
logging_color_formatter-1.1.0.dist-info/RECORD
