Metadata-Version: 2.1
Name: logging-color-formatter
Version: 1.1.0
Summary: A colored logging formatter
Author-email: Mathieu Leplatre <mathieu@leplat.re>
License: Copyright 2017 - Mathieu Leplatre
Project-URL: Repository, https://github.com/leplatrem/logging-color-formatter
Keywords: logging
Classifier: Programming Language :: Python
Classifier: Programming Language :: Python :: 3
Classifier: License :: OSI Approved :: Apache Software License
License-File: LICENSE
Requires-Dist: colorama
Provides-Extra: dev
Requires-Dist: pytest ; extra == 'dev'
